consent_app/__init__.py
consent_app/apps.py
consent_app/baker_recipes.py
consent_app/models.py
consent_app/visit_schedules.py
edc_consent/__init__.py
edc_consent/actions.py
edc_consent/admin_site.py
edc_consent/apps.py
edc_consent/auth_objects.py
edc_consent/auths.py
edc_consent/choices.py
edc_consent/consent_definition.py
edc_consent/consent_definition_extension.py
edc_consent/constants.py
edc_consent/exceptions.py
edc_consent/fieldsets.py
edc_consent/forms.py
edc_consent/managers.py
edc_consent/navbars.py
edc_consent/site_consents.py
edc_consent/stubs.py
edc_consent/system_checks.py
edc_consent/urls.py
edc_consent/utils.py
edc_consent/validators.py
edc_consent/wsgi.py
edc_consent/field_mixins/__init__.py
edc_consent/field_mixins/citizen_fields_mixin.py
edc_consent/field_mixins/identity_fields_mixin.py
edc_consent/field_mixins/personal_fields_mixin.py
edc_consent/field_mixins/review_fields_mixin.py
edc_consent/field_mixins/sample_collection_fields_mixin.py
edc_consent/field_mixins/scored_review_fields_mixin.py
edc_consent/field_mixins/site_fields_mixin.py
edc_consent/field_mixins/verification_fields_mixin.py
edc_consent/field_mixins/vulnerability_fields_mixin.py
edc_consent/form_validators/__init__.py
edc_consent/form_validators/consent_definition_form_validator_mixin.py
edc_consent/form_validators/subject_consent_form_validator.py
edc_consent/migrations/0001_initial.py
edc_consent/migrations/0002_alter_edcpermissions_device_created_and_more.py
edc_consent/migrations/0003_edcpermissions_locale_created_and_more.py
edc_consent/migrations/0004_alter_edcpermissions_options_and_more.py
edc_consent/migrations/__init__.py
edc_consent/model_mixins/__init__.py
edc_consent/model_mixins/consent_extension_model_mixin.py
edc_consent/model_mixins/consent_model_mixin.py
edc_consent/model_mixins/consent_version_model_mixin.py
edc_consent/model_mixins/requires_consent_fields_model_mixin.py
edc_consent/modeladmin_mixins/__init__.py
edc_consent-1.0.3.dist-info/AUTHORS
edc_consent-1.0.3.dist-info/LICENSE
edc_consent-1.0.3.dist-info/METADATA
edc_consent-1.0.3.dist-info/WHEEL
edc_consent-1.0.3.dist-info/top_level.txt
edc_consent-1.0.3.dist-info/RECORD
